MANIFEST.in
README.md
requirements.txt
setup.py
app_page_core/Callback.py
app_page_core/Children.py
app_page_core/LocalStore.py
app_page_core/Page.py
app_page_core/Param.py
app_page_core/Store.py
app_page_core/__init__.py
app_page_core/global_variable.py
app_page_core.egg-info/PKG-INFO
app_page_core.egg-info/SOURCES.txt
app_page_core.egg-info/dependency_links.txt
app_page_core.egg-info/not-zip-safe
app_page_core.egg-info/requires.txt
app_page_core.egg-info/top_level.txt