Metadata-Version: 2.1
Name: app-page-core
Version: 0.0.6
Summary: python page application framework
Home-page: https://github.com/xiaohuicat/python-app-page-core
Author: xiaohuicat
Author-email: 1258702350@qq.com
License: MIT
Requires-Dist: nanoid
